openmcp/PKG-INFO
openmcp/__init__.py
openmcp/example.py
openmcp/pyproject.toml
openmcp/setup.cfg
openmcp/telemetry.py
openmcp/test_search_text.py
openmcp/__pycache__/__init__.cpython-311.pyc
openmcp/backends/__init__.py
openmcp/backends/base_provider.py
openmcp/backends/search_backend.py
openmcp/backends/vanilla_backend.py
openmcp/backends/__pycache__/__init__.cpython-311.pyc
openmcp/backends/__pycache__/base_provider.cpython-311.pyc
openmcp/backends/__pycache__/vanilla_backend.cpython-311.pyc
openmcp/build/lib/openmcp/__init__.py
openmcp/build/lib/openmcp/example.py
openmcp/build/lib/openmcp/telemetry.py
openmcp/build/lib/openmcp/test_search_text.py
openmcp/build/lib/openmcp/backends/__init__.py
openmcp/build/lib/openmcp/backends/base_provider.py
openmcp/build/lib/openmcp/backends/search_backend.py
openmcp/build/lib/openmcp/backends/vanilla_backend.py
openmcp/build/lib/openmcp/core/__init__.py
openmcp/build/lib/openmcp/core/widget.py
openmcp/build/lib/openmcp_cli/__init__.py
openmcp/core/__init__.py
openmcp/core/widget.py
openmcp/core/__pycache__/__init__.cpython-311.pyc
openmcp/core/__pycache__/widget.cpython-311.pyc
openmcp/openmcp_cli/__init__.py
openmcp/openmcp_cli/__pycache__/__init__.cpython-311.pyc
openmcp/openmcp_sdk.egg-info/PKG-INFO
openmcp/openmcp_sdk.egg-info/SOURCES.txt
openmcp/openmcp_sdk.egg-info/dependency_links.txt
openmcp/openmcp_sdk.egg-info/entry_points.txt
openmcp/openmcp_sdk.egg-info/requires.txt
openmcp/openmcp_sdk.egg-info/top_level.txt
openmcp/templates/chatgpt/README.md
openmcp/templates/chatgpt/main.py
openmcp/templates/chatgpt/requirements.txt
openmcp/templates/chatgpt/assets/build.mjs
openmcp/templates/chatgpt/assets/package.json
openmcp/templates/chatgpt/assets/vite.config.mts
openmcp/templates/chatgpt/assets/entrypoints/pizzaz-albums.html
openmcp/templates/chatgpt/assets/entrypoints/pizzaz-carousel.html
openmcp/templates/chatgpt/assets/entrypoints/pizzaz-list.html
openmcp/templates/chatgpt/assets/entrypoints/pizzaz-shop.html
openmcp/templates/chatgpt/assets/entrypoints/pizzaz.html
openmcp/templates/chatgpt/assets/src/index.css
openmcp/templates/chatgpt/assets/src/types.ts
openmcp/templates/chatgpt/assets/src/use-display-mode.ts
openmcp/templates/chatgpt/assets/src/use-max-height.ts
openmcp_sdk-0.2.20.dist-info/METADATA
openmcp_sdk-0.2.20.dist-info/WHEEL
openmcp_sdk-0.2.20.dist-info/entry_points.txt
openmcp_sdk-0.2.20.dist-info/top_level.txt
openmcp_sdk-0.2.20.dist-info/RECORD
